independentsoft
