Metadata-Version: 2.1
Name: independentsoft.msg
Version: 1.6
Summary: Outlook .msg file format module
Home-page: http://www.independentsoft.de
Author: Independentsoft
Author-email: info@independentsoft.de
License: Other/Proprietary License
Download-URL: http://www.independentsoft.de
Keywords: outlook,msg,independentsoft
Platform: UNKNOWN
Classifier: Development Status :: 5 - Production/Stable
Classifier: Intended Audience :: Developers
Classifier: Topic :: Software Development :: Libraries :: Python Modules
Classifier: Topic :: Communications :: Email
Classifier: Topic :: Office/Business
Classifier: License :: Other/Proprietary License
Classifier: Programming Language :: Python :: 3
Requires-Python: >=3.3
